ndtiler.py
ndtiler-0.1.0.dist-info/licenses/LICENSE.txt
ndtiler-0.1.0.dist-info/METADATA
ndtiler-0.1.0.dist-info/WHEEL
ndtiler-0.1.0.dist-info/top_level.txt
ndtiler-0.1.0.dist-info/RECORD
