Metadata-Version: 2.4
Name: ndtiler
Version: 0.1.0
Summary: Lightweight package for iterative tiling over N-dimensional arrays
Home-page: https://github.com/ryanirl/ndtiler
Author: Ryan 'RyanIRL' Peters
Author-email: RyanIRL@icloud.com
Project-URL: Bug Reports, https://github.com/ryanirl/ndtiler/issues
Project-URL: Source, https://github.com/ryanirl/ndtiler
Keywords: array,tiling,numpy,image processing,deep learning
Classifier: Development Status :: 3 - Alpha
Classifier: Intended Audience :: Developers
Classifier: Intended Audience :: Science/Research
Classifier: License :: OSI Approved :: MIT License
Classifier: Programming Language :: Python :: 3
Classifier: Programming Language :: Python :: 3.7
Classifier: Programming Language :: Python :: 3.8
Classifier: Programming Language :: Python :: 3.9
Classifier: Programming Language :: Python :: 3.10
Classifier: Programming Language :: Python :: 3.11
Classifier: Topic :: Scientific/Engineering
Classifier: Topic :: Scientific/Engineering :: Image Processing
Classifier: Topic :: Scientific/Engineering :: Artificial Intelligence
Requires-Python: >=3.7
License-File: LICENSE.txt
Dynamic: author
Dynamic: author-email
Dynamic: classifier
Dynamic: description
Dynamic: description-content-type
Dynamic: home-page
Dynamic: keywords
Dynamic: license-file
Dynamic: project-url
Dynamic: requires-python
Dynamic: summary
